counter.sv
module counter (
    input  logic clk,
    input  logic rst_n,
    output logic [3:0] count
);

    always_ff @(posedge clk or negedge rst_n) begin
        if (!rst_n)
            count <= 4'd0;
        else
            count <= count + 1;
    end

endmodule

tb_counter.sv
`timescale 1ns/1ps

module tb_counter;

    logic clk;
    logic rst_n;
    logic [3:0] count;

    // Instantiate the counter
    counter uut (
        .clk(clk),
        .rst_n(rst_n),
        .count(count)
    );

    // Clock generation: 10ns period
    always #5 clk = ~clk;

    initial begin
        $dumpfile("counter.vcd");  // optional for waveform viewing in GTKWave
        $dumpvars(0, tb_counter);

        // Initialize signals
        clk = 0;
        rst_n = 0;

        // Reset pulse
        #10 rst_n = 1;

        // Let the simulation run for some time
        #100;

        $finish;
    end

endmodule

counter.vcd
$date
	Wed Jul 02 22:16:14 2025
$end
$version
	ModelSim Version 2020.1
$end
$timescale
	1ps
$end

$scope module tb_counter $end
$var reg 1 ! clk $end
$var reg 1 " rst_n $end
$var reg 4 # count [3:0] $end

$scope module uut $end
$var wire 1 $ clk $end
$var wire 1 % rst_n $end
$var reg 4 & count [3:0] $end
$upscope $end
$upscope $end
$enddefinitions $end
#0
$dumpvars
0!
0"
b0 #
b0 &
0$
0%
$end
#5000
1!
1$
#10000
1"
0!
1%
0$
#15000
1!
1$
b1 &
b1 #
#20000
0!
0$
#25000
1!
1$
b10 &
b10 #
#30000
0!
0$
#35000
1!
1$
b11 &
b11 #
#40000
0!
0$
#45000
1!
1$
b100 &
b100 #
#50000
0!
0$
#55000
1!
1$
b101 &
b101 #
#60000
0!
0$
#65000
1!
1$
b110 &
b110 #
#70000
0!
0$
#75000
1!
1$
b111 &
b111 #
#80000
0!
0$
#85000
1!
1$
b1000 &
b1000 #
#90000
0!
0$
#95000
1!
1$
b1001 &
b1001 #
